MANIFEST.in
setup.py
vr/__init__.py
vr/commands.py
vr/gunicorn_config.py
vr/manage.py
vr/settings.py
vr/urls.py
vr/wsgi.py
vr.egg-info/PKG-INFO
vr.egg-info/SOURCES.txt
vr.egg-info/dependency_links.txt
vr.egg-info/entry_points.txt
vr.egg-info/requires.txt
vr.egg-info/top_level.txt
vr/api/__init__.py
vr/api/resources.py
vr/api/urls.py
vr/api/views.py
vr/deployment/__init__.py
vr/deployment/admin.py
vr/deployment/context_processors.py
vr/deployment/events.py
vr/deployment/feeds.py
vr/deployment/fields.py
vr/deployment/forms.py
vr/deployment/models.py
vr/deployment/storages.py
vr/deployment/tasks.py
vr/deployment/utils.py
vr/deployment/views.py
vr/deployment/balancer/__init__.py
vr/deployment/balancer/base.py
vr/deployment/balancer/dummy.py
vr/deployment/balancer/nginx.py
vr/deployment/balancer/varnish.py
vr/deployment/balancer/zxtm.py
vr/deployment/migrations/0001_initial.py
vr/deployment/migrations/0002_cascading_yaml_config.py
vr/deployment/migrations/0003_use_profile_names.py
vr/deployment/migrations/0004_auto__chg_field_release_config__add_field_build_tag.py
vr/deployment/migrations/0005_auto__add_field_build_time.py
vr/deployment/migrations/0006_auto__del_unique_profile_name__add_unique_profile_app_name__chg_field_.py
vr/deployment/migrations/0007_auto__add_field_build_start_time__add_field_build_end_time__chg_field_.py
vr/deployment/migrations/0008_auto__chg_field_build_start_time.py
vr/deployment/migrations/0009_copy_start_time.py
vr/deployment/migrations/0010_auto__del_field_build_time.py
vr/deployment/migrations/0011_auto__add_field_build_status.py
vr/deployment/migrations/0012_auto__add_squad__add_swarm__del_field_release_profile_name__add_field_.py
vr/deployment/migrations/0013_auto__del_field_swarm_automate__add_field_swarm_active.py
vr/deployment/migrations/0014_auto__chg_field_release_hash.py
vr/deployment/migrations/0015_auto__add_unique_swarm_profile_squad_proc_name.py
vr/deployment/migrations/0016_auto__chg_field_swarm_pool.py
vr/deployment/migrations/0017_auto__add_portlock__add_unique_portlock_host_port.py
vr/deployment/migrations/0018_auto__add_field_portlock_created_time.py
