Metadata-Version: 1.0
Name: vr
Version: 2.1.2
Summary: Velociraptor Django project.
Home-page: UNKNOWN
Author: Brent Tubbs
Author-email: brent.tubbs@gmail.com
License: UNKNOWN
Platform: UNKNOWN
